{
  "version": "2.0",
  "lastUpdated": "2026-03-03T12:17:34.217Z",
  "activeFeatures": [
    "SG100",
    "data",
    "vote",
    "results",
    "voices"
  ],
  "primaryFeature": "SG100",
  "features": {
    "SG100": {
      "phase": "do",
      "phaseNumber": 3,
      "matchRate": null,
      "iterationCount": 0,
      "requirements": [],
      "documents": {},
      "timestamps": {
        "started": "2026-02-24T08:44:38.220Z",
        "lastUpdated": "2026-03-03T12:17:34.217Z"
      },
      "lastFile": "E:\\work\\web\\SG100\\src\\components\\Header.tsx"
    },
    "data": {
      "phase": "do",
      "phaseNumber": 3,
      "matchRate": null,
      "iterationCount": 0,
      "requirements": [],
      "documents": {},
      "timestamps": {
        "started": "2026-02-24T08:46:11.667Z",
        "lastUpdated": "2026-02-24T08:46:11.667Z"
      },
      "lastFile": "E:\\work\\web\\SG100\\src\\data\\pledges.ts"
    },
    "vote": {
      "phase": "do",
      "phaseNumber": 3,
      "matchRate": null,
      "iterationCount": 0,
      "requirements": [],
      "documents": {},
      "timestamps": {
        "started": "2026-02-24T08:50:12.627Z",
        "lastUpdated": "2026-02-24T08:50:12.627Z"
      },
      "lastFile": "E:\\work\\web\\SG100\\src\\app\\vote\\page.tsx"
    },
    "results": {
      "phase": "do",
      "phaseNumber": 3,
      "matchRate": null,
      "iterationCount": 0,
      "requirements": [],
      "documents": {},
      "timestamps": {
        "started": "2026-02-24T08:50:47.950Z",
        "lastUpdated": "2026-02-24T13:52:23.447Z"
      },
      "lastFile": "E:\\work\\web\\SG100\\src\\app\\results\\page.tsx"
    },
    "voices": {
      "phase": "do",
      "phaseNumber": 3,
      "matchRate": null,
      "iterationCount": 0,
      "requirements": [],
      "documents": {},
      "timestamps": {
        "started": "2026-03-02T05:10:48.617Z",
        "lastUpdated": "2026-03-02T06:26:19.025Z"
      },
      "lastFile": "E:\\work\\web\\SG100\\src\\app\\voices\\page.tsx"
    }
  },
  "pipeline": {
    "currentPhase": 1,
    "level": "Dynamic",
    "phaseHistory": []
  },
  "session": {
    "startedAt": "2026-02-24T08:03:10.087Z",
    "onboardingCompleted": false,
    "lastActivity": "2026-03-03T12:17:34.217Z"
  },
  "history": [
    {
      "timestamp": "2026-02-24T08:44:38.220Z",
      "feature": "SG100",
      "phase": "do",
      "action": "updated"
    },
    {
      "timestamp": "2026-02-24T08:44:43.369Z",
      "feature": "SG100",
      "phase": "do",
      "action": "updated"
    },
    {
      "timestamp": "2026-02-24T08:44:48.798Z",
      "feature": "SG100",
      "phase": "do",
      "action": "updated"
    },
    {
      "timestamp": "2026-02-24T08:46:11.667Z",
      "feature": "data",
      "phase": "do",
      "action": "updated"
    },
    {
      "timestamp": "2026-02-24T08:47:23.032Z",
      "feature": "SG100",
      "phase": "do",
      "action": "updated"
    },
    {
      "timestamp": "2026-02-24T08:47:33.191Z",
      "feature": "SG100",
      "phase": "do",
      "action": "updated"
    },
    {
      "timestamp": "2026-02-24T08:47:47.959Z",
      "feature": "SG100",
      "phase": "do",
      "action": "updated"
    },
    {
      "timestamp": "2026-02-24T08:47:59.128Z",
      "feature": "SG100",
      "phase": "do",
      "action": "updated"
    },
    {
      "timestamp": "2026-02-24T08:48:09.001Z",
      "feature": "SG100",
      "phase": "do",
      "action": "updated"
    },
    {
      "timestamp": "2026-02-24T08:48:16.534Z",
      "feature": "SG100",
      "phase": "do",
      "action": "updated"
    },
    {
      "timestamp": "2026-02-24T08:48:24.610Z",
      "feature": "SG100",
      "phase": "do",
      "action": "updated"
    },
    {
      "timestamp": "2026-02-24T08:48:32.302Z",
      "feature": "SG100",
      "phase": "do",
      "action": "updated"
    },
    {
      "timestamp": "2026-02-24T08:48:39.275Z",
      "feature": "SG100",
      "phase": "do",
      "action": "updated"
    },
    {
      "timestamp": "2026-02-24T08:48:52.588Z",
      "feature": "SG100",
      "phase": "do",
      "action": "updated"
    },
    {
      "timestamp": "2026-02-24T08:49:47.070Z",
      "feature": "SG100",
      "phase": "do",
      "action": "updated"
    },
    {
      "timestamp": "2026-02-24T08:50:12.627Z",
      "feature": "vote",
      "phase": "do",
      "action": "updated"
    },
    {
      "timestamp": "2026-02-24T08:50:47.950Z",
      "feature": "results",
      "phase": "do",
      "action": "updated"
    },
    {
      "timestamp": "2026-02-24T08:51:34.795Z",
      "feature": "SG100",
      "phase": "do",
      "action": "updated"
    },
    {
      "timestamp": "2026-02-24T08:54:45.347Z",
      "feature": "SG100",
      "phase": "do",
      "action": "updated"
    },
    {
      "timestamp": "2026-02-24T09:03:37.408Z",
      "feature": "SG100",
      "phase": "do",
      "action": "updated"
    },
    {
      "timestamp": "2026-02-24T09:03:44.430Z",
      "feature": "SG100",
      "phase": "do",
      "action": "updated"
    },
    {
      "timestamp": "2026-02-24T09:03:49.844Z",
      "feature": "SG100",
      "phase": "do",
      "action": "updated"
    },
    {
      "timestamp": "2026-02-24T13:36:52.253Z",
      "feature": "SG100",
      "phase": "do",
      "action": "updated"
    },
    {
      "timestamp": "2026-02-24T13:52:08.897Z",
      "feature": "SG100",
      "phase": "do",
      "action": "updated"
    },
    {
      "timestamp": "2026-02-24T13:52:14.778Z",
      "feature": "SG100",
      "phase": "do",
      "action": "updated"
    },
    {
      "timestamp": "2026-02-24T13:52:23.447Z",
      "feature": "results",
      "phase": "do",
      "action": "updated"
    },
    {
      "timestamp": "2026-03-02T05:09:23.002Z",
      "feature": "SG100",
      "phase": "do",
      "action": "updated"
    },
    {
      "timestamp": "2026-03-02T05:09:30.094Z",
      "feature": "SG100",
      "phase": "do",
      "action": "updated"
    },
    {
      "timestamp": "2026-03-02T05:09:50.391Z",
      "feature": "SG100",
      "phase": "do",
      "action": "updated"
    },
    {
      "timestamp": "2026-03-02T05:10:06.374Z",
      "feature": "SG100",
      "phase": "do",
      "action": "updated"
    },
    {
      "timestamp": "2026-03-02T05:10:19.517Z",
      "feature": "SG100",
      "phase": "do",
      "action": "updated"
    },
    {
      "timestamp": "2026-03-02T05:10:31.139Z",
      "feature": "SG100",
      "phase": "do",
      "action": "updated"
    },
    {
      "timestamp": "2026-03-02T05:10:48.617Z",
      "feature": "voices",
      "phase": "do",
      "action": "updated"
    },
    {
      "timestamp": "2026-03-02T05:10:55.147Z",
      "feature": "SG100",
      "phase": "do",
      "action": "updated"
    },
    {
      "timestamp": "2026-03-02T05:11:27.745Z",
      "feature": "SG100",
      "phase": "do",
      "action": "updated"
    },
    {
      "timestamp": "2026-03-02T06:26:17.550Z",
      "feature": "SG100",
      "phase": "do",
      "action": "updated"
    },
    {
      "timestamp": "2026-03-02T06:26:18.421Z",
      "feature": "SG100",
      "phase": "do",
      "action": "updated"
    },
    {
      "timestamp": "2026-03-02T06:26:19.025Z",
      "feature": "voices",
      "phase": "do",
      "action": "updated"
    },
    {
      "timestamp": "2026-03-02T06:26:24.865Z",
      "feature": "SG100",
      "phase": "do",
      "action": "updated"
    },
    {
      "timestamp": "2026-03-02T06:26:55.086Z",
      "feature": "SG100",
      "phase": "do",
      "action": "updated"
    },
    {
      "timestamp": "2026-03-02T06:28:22.679Z",
      "feature": "SG100",
      "phase": "do",
      "action": "updated"
    },
    {
      "timestamp": "2026-03-03T10:26:10.181Z",
      "feature": "SG100",
      "phase": "do",
      "action": "updated"
    },
    {
      "timestamp": "2026-03-03T10:30:45.114Z",
      "feature": "SG100",
      "phase": "do",
      "action": "updated"
    },
    {
      "timestamp": "2026-03-03T10:31:37.142Z",
      "feature": "SG100",
      "phase": "do",
      "action": "updated"
    },
    {
      "timestamp": "2026-03-03T10:32:43.792Z",
      "feature": "SG100",
      "phase": "do",
      "action": "updated"
    },
    {
      "timestamp": "2026-03-03T10:32:50.343Z",
      "feature": "SG100",
      "phase": "do",
      "action": "updated"
    },
    {
      "timestamp": "2026-03-03T10:32:59.964Z",
      "feature": "SG100",
      "phase": "do",
      "action": "updated"
    },
    {
      "timestamp": "2026-03-03T10:33:10.584Z",
      "feature": "SG100",
      "phase": "do",
      "action": "updated"
    },
    {
      "timestamp": "2026-03-03T10:33:17.583Z",
      "feature": "SG100",
      "phase": "do",
      "action": "updated"
    },
    {
      "timestamp": "2026-03-03T10:33:25.356Z",
      "feature": "SG100",
      "phase": "do",
      "action": "updated"
    },
    {
      "timestamp": "2026-03-03T10:41:01.665Z",
      "feature": "SG100",
      "phase": "do",
      "action": "updated"
    },
    {
      "timestamp": "2026-03-03T10:41:13.644Z",
      "feature": "SG100",
      "phase": "do",
      "action": "updated"
    },
    {
      "timestamp": "2026-03-03T12:10:49.039Z",
      "feature": "SG100",
      "phase": "do",
      "action": "updated"
    },
    {
      "timestamp": "2026-03-03T12:10:55.195Z",
      "feature": "SG100",
      "phase": "do",
      "action": "updated"
    },
    {
      "timestamp": "2026-03-03T12:11:01.122Z",
      "feature": "SG100",
      "phase": "do",
      "action": "updated"
    },
    {
      "timestamp": "2026-03-03T12:11:07.622Z",
      "feature": "SG100",
      "phase": "do",
      "action": "updated"
    },
    {
      "timestamp": "2026-03-03T12:11:59.993Z",
      "feature": "SG100",
      "phase": "do",
      "action": "updated"
    },
    {
      "timestamp": "2026-03-03T12:12:03.540Z",
      "feature": "SG100",
      "phase": "do",
      "action": "updated"
    },
    {
      "timestamp": "2026-03-03T12:12:08.688Z",
      "feature": "SG100",
      "phase": "do",
      "action": "updated"
    },
    {
      "timestamp": "2026-03-03T12:16:23.010Z",
      "feature": "SG100",
      "phase": "do",
      "action": "updated"
    },
    {
      "timestamp": "2026-03-03T12:17:29.322Z",
      "feature": "SG100",
      "phase": "do",
      "action": "updated"
    },
    {
      "timestamp": "2026-03-03T12:17:34.217Z",
      "feature": "SG100",
      "phase": "do",
      "action": "updated"
    }
  ]
}